zettelkasten_cli/__init__.py
zettelkasten_cli/config.py
zettelkasten_cli/exceptions.py
zettelkasten_cli/main.py
zettelkasten_cli/output.py
zettelkasten_cli/models/__init__.py
zettelkasten_cli/models/note.py
zettelkasten_cli/models/periodic_note.py
zettelkasten_cli/services/__init__.py
zettelkasten_cli/services/editor.py
zettelkasten_cli/services/template.py
zettelkasten_cli-1.0.3.dist-info/METADATA
zettelkasten_cli-1.0.3.dist-info/WHEEL
zettelkasten_cli-1.0.3.dist-info/entry_points.txt
zettelkasten_cli-1.0.3.dist-info/RECORD
