Metadata-Version: 2.4
Name: zettelkasten-cli
Version: 1.0.3
Summary: A CLI for managing your Neovim + Obsidian Zettelkasten
Author: Mischa van den Burg
Requires-Python: >=3.14
Requires-Dist: typer[all]>=0.12.3
